lazylist.py
lazylist-0.9.0.dist-info/DESCRIPTION.rst
lazylist-0.9.0.dist-info/METADATA
lazylist-0.9.0.dist-info/RECORD
lazylist-0.9.0.dist-info/WHEEL
lazylist-0.9.0.dist-info/metadata.json
lazylist-0.9.0.dist-info/top_level.txt
